saif/__init__.py
saif/core.py
saif-100.78.dist-info/METADATA
saif-100.78.dist-info/WHEEL
saif-100.78.dist-info/top_level.txt
saif-100.78.dist-info/RECORD
